{".FVER":1,".DATE_CREATED":1550857787305,".FILE_VERSION":5,".BIRTH_SESSION":"yiw99tznnitg8zpotjwnp4pac8y4uo0jxmiw68ajgtqej6t3fghvaxvcvj7gyyql",".OID":"x2tgsxn92rew7at4",".MODIFIED_BY":"8uqi0rivp58tr183",".ORIGINAL_FILE_SIZE":"2820",".CREATOR":"8uqi0rivp58tr183",".FILE_SIZE":1057,".LAST_SESSION":"yiw99tznnitg8zpotjwnp4pac8y4uo0jxmiw68ajgtqej6t3fghvaxvcvj7gyyql",".NAME":"ParallelProcessor",".CLASS":"App",".DATE_MODIFIED":1550858755944,".FILE_ENCODING":"ds1_1",".VERSION":6,".FILE_MIME":"text/javascript; charset=utf-8",".FILE_UPLOADED":1550858755944}