{".FVER":1,".DATE_CREATED":1535639408969,".FILE_VERSION":1,".BIRTH_SESSION":"2itfjkjj2d81eym9b8u2v5sz39s2cj54rpa1zkasn9ksxwszvcsh7b61aotcxp7e",".MODIFIED_BY":"8uqi0rivp58tr183",".OID":"gkqmfgccmkpb8inq",".ORIGINAL_FILE_SIZE":"9588",".CREATOR":"8uqi0rivp58tr183",".FILE_SIZE":9018,".LAST_SESSION":"2itfjkjj2d81eym9b8u2v5sz39s2cj54rpa1zkasn9ksxwszvcsh7b61aotcxp7e",".IMAGE_HEIGHT":256,".NAME":"power_icon.png",".FILE_NAME":"power_icon.png",".IMAGE_WIDTH":256,".CLASS":"Image",".DATE_MODIFIED":1535639409087,".FILE_ENCODING":"ds1_1",".VERSION":2,".FILE_MIME":"image/png",".FILE_UPLOADED":1535639409230,".FILE_MODIFIED":1525918884000}