{".FVER":1,".DATE_CREATED":1656534488124,".T":563433,".FILE_VERSION":6,".BIRTH_SESSION":"h14f7k3qdvg0tcp6zd7p1s6grbe18cxs6x11tpx4q3wjhhbsja1y6yvfpz06j8un",".LIST":{"5mi055kxtsay2zht":{".NAME":"webGL",".CLASS":"App"}},".OID":"b1ycg0nbmolihcx1",".ORIGINAL_FILE_SIZE":1496,".CREATOR":"8uqi0rivp58tr183",".MIME":"text/javascript; charset=utf-8",".NAME":"MatCap Viewer","Assets":"{\"webGL\":{\"id\":\"5mi055kxtsay2zht\",\"type\":\"App\"}}",".CLASS":"App",".DATE_MODIFIED":1656536034493,".FILE_ENCODING":"ds1_1",".VERSION":9}