{".FVER":1,".DATE_CREATED":1537761217303,".FILE_VERSION":10,".BIRTH_SESSION":"8gz94lrsagr526ojxploonwknhqfmaclh1kcc2vd9c928obw4naj0xtd5aiiblti",".LIST":{"3qhciuvplxinrvgc":{".NAME":"VNlogo_mask.png",".CLASS":"Image"},"2g8cc5przdjap3la":{".NAME":"GLObject",".CLASS":"AppData"},"6obqzfxdhm1l6xzc":{".NAME":"opn_logo.png",".CLASS":"Image"}},".MODIFIED_BY":"8uqi0rivp58tr183",".OID":"kc3p484i552qske9",".ORIGINAL_FILE_SIZE":"922",".CREATOR":"8uqi0rivp58tr183",".FILE_SIZE":455,".LAST_SESSION":"fyfdfvsn9x9p1b8z1s7kmpdrz1hsew4jlanrv64vt4al59bwr874nbmc3tv7gqhr",".NAME":"GLWatermark","Assets":"{\"GLObject\":{\"id\":\"2g8cc5przdjap3la\",\"type\":\"AppData\"},\"VNlogo_mask.png\":{\"id\":\"3qhciuvplxinrvgc\",\"type\":\"Image\"},\"opn_logo.png\":{\"id\":\"6obqzfxdhm1l6xzc\",\"type\":\"Image\"}}",".CLASS":"App",".DATE_MODIFIED":1543869578295,".FILE_ENCODING":"ds1_1",".VERSION":19,".FILE_MIME":"text/javascript; charset=utf-8",".FILE_UPLOADED":1543869578295}