{".FVER":1,".DATE_CREATED":1537758913416,".FILE_VERSION":23,".BIRTH_SESSION":"8gz94lrsagr526ojxploonwknhqfmaclh1kcc2vd9c928obw4naj0xtd5aiiblti",".LIST":{"1zw2dotau8jvfsbp":{".NAME":"mat4",".CLASS":"AppData"},"mcbfj4gh6swc9d22":{".NAME":"GLShader",".CLASS":"AppData"},"usk12qc9vea71nwr":{".NAME":"GLTexture",".CLASS":"AppData"}},".MODIFIED_BY":"8uqi0rivp58tr183",".OID":"11jhuix8rs5d5ago",".ORIGINAL_FILE_SIZE":"8260",".CREATOR":"8uqi0rivp58tr183",".FILE_SIZE":2037,".LAST_SESSION":"mvjufzolixi2lota6xsrmeznnf3rnjr040kaqzlzmury8by5yhmalboyhigurxkl",".NAME":"GLPicker","Assets":"{\"GLShader\":{\"id\":\"mcbfj4gh6swc9d22\",\"type\":\"AppData\"},\"GLTexture\":{\"id\":\"usk12qc9vea71nwr\",\"type\":\"AppData\"},\"mat4\":{\"id\":\"1zw2dotau8jvfsbp\",\"type\":\"AppData\"}}",".CLASS":"App",".DATE_MODIFIED":1540175181513,".FILE_ENCODING":"ds1_1",".VERSION":31,".FILE_MIME":"text/javascript; charset=utf-8",".FILE_UPLOADED":1540175181513}