{".FVER":1,".DATE_CREATED":1597263321069,".T":1528248795,".FILE_VERSION":25,".BIRTH_SESSION":"07y2plxzwo4uyg5u52ibsl7unth343foeawazmovoub0l75pfpoqlra2lf36zqq8",".LIST":{"uev92ntkh16iskau":{".NAME":"Button",".CLASS":"App"}},".OID":"okoaogjvwb1t9rak",".ORIGINAL_FILE_SIZE":2231,".CREATOR":"8uqi0rivp58tr183",".MIME":"text/javascript; charset=utf-8",".NAME":"ToggleButton","Assets":"{\"Button\":{\"id\":\"uev92ntkh16iskau\",\"type\":\"App\"}}",".CLASS":"App",".DATE_MODIFIED":1678135965913,".FILE_ENCODING":"ds1_1",".VERSION":31}